contextkit/__init__.py
contextkit/_modidx.py
contextkit/read.py
contextkit-0.0.10.dist-info/licenses/LICENSE
contextkit-0.0.10.dist-info/METADATA
contextkit-0.0.10.dist-info/WHEEL
contextkit-0.0.10.dist-info/entry_points.txt
contextkit-0.0.10.dist-info/top_level.txt
contextkit-0.0.10.dist-info/RECORD
