Metadata-Version: 2.4
Name: contextkit
Version: 0.0.10
Summary: Reusable contexts for LLMs
Home-page: https://github.com/AnswerDotAI/contextkit
Author: Isaac Flath
Author-email: isaac.flath@gmail.com
License: Apache Software License 2.0
Keywords: nbdev jupyter notebook python
Classifier: Development Status :: 4 - Beta
Classifier: Intended Audience :: Developers
Classifier: Natural Language :: English
Classifier: Programming Language :: Python :: 3.10
Classifier: Programming Language :: Python :: 3.11
Classifier: Programming Language :: Python :: 3.12
Classifier: License :: OSI Approved :: Apache Software License
Requires-Python: >=3.10
License-File: LICENSE
Requires-Dist: python-fasthtml
Requires-Dist: httpx
Requires-Dist: toolslm
Requires-Dist: fastcore
Requires-Dist: llms-txt
Requires-Dist: pypdf
Requires-Dist: youtube_transcript_api
Requires-Dist: pytube
Requires-Dist: playwrightnb
Provides-Extra: dev
Dynamic: author
Dynamic: author-email
Dynamic: classifier
Dynamic: description
Dynamic: description-content-type
Dynamic: home-page
Dynamic: keywords
Dynamic: license
Dynamic: license-file
Dynamic: provides-extra
Dynamic: requires-dist
Dynamic: requires-python
Dynamic: summary
